{
        "0": {"name": "DecisionForest",
            "version": {
                "0": "func",
                "1": "func",
                "2": "func",
                "3": "func",
                "4": "func",
                "5": "func",
                "6": "func",
                "7": "func",
                "8": "func",
                "9": "func"
                }
            },
        "1": {"name": "DecisionTree",
            "version": {
                "0": "func",
                "1": "func",
                "2": "func",
                "3": "func",
                "4": "func",
                "5": "func",
                "6": "func",
                "7": "func",
                "8": "func",
                "9": "func"
                }
            },
        "2": {"name": "NaiveBayes",
            "version": {
                "0": "func",
                "1": "func",
                "2": "func",
                "3": "func",
                "4": "func",
                "5": "func",
                "6": "func",
                "7": "func",
                "8": "func",
                "9": "func"
                }
            },
        "3": {"name": "SupportVectorMachine",
            "version": {
                "0": "func",
                "1": "func",
                "2": "func",
                "3": "func",
                "4": "func",
                "5": "func",
                "6": "func",
                "7": "func",
                "8": "func",
                "9": "func"
                }
            },
        "4": {"name": "StochasticGradient",
            "version": {
                "0": "func",
                "1": "func",
                "2": "func",
                "3": "func",
                "4": "func",
                "5": "func",
                "6": "func",
                "7": "func",
                "8": "func",
                "9": "func"
                }
            },
        "5": {"name": "KNearestNeighbors",
            "version": {
                "0": "func",
                "1": "func",
                "2": "func",
                "3": "func",
                "4": "func",
                "5": "func",
                "6": "func",
                "7": "func",
                "8": "func",
                "9": "func"
                }
            },
        "6": {"name": "AdaBoost",
            "version": {
                "0": "func",
                "1": "func",
                "2": "func",
                "3": "func",
                "4": "func",
                "5": "func",
                "6": "func",
                "7": "func",
                "8": "func",
                "9": "func"
                }
            },
        "7": {"name": "Ridge",
            "version": {
                "0": "func",
                "1": "func",
                "2": "func",
                "3": "func",
                "4": "func",
                "5": "func",
                "6": "func",
                "7": "func",
                "8": "func",
                "9": "func"
                }
            },
        "8": {"name": "PassiveAggressive",
            "version": {
                "0": "func",
                "1": "func",
                "2": "func",
                "3": "func",
                "4": "func",
                "5": "func",
                "6": "func",
                "7": "func",
                "8": "func",
                "9": "func"
                }
            },
        "9": {"name": "LinearDiscriminantAnalysis",
            "version": {
                "0": "func",
                "1": "func",
                "2": "func",
                "3": "func",
                "4": "func",
                "5": "func",
                "6": "func",
                "7": "func",
                "8": "func",
                "9": "func"
                }
            }
    }